bruhapy/__init__.py
bruhapy/imageendpoints.py
bruhapy/misc.py
bruhapy/textendpoints.py
bruhapy-2020.12.13.dist-info/LICENSE
bruhapy-2020.12.13.dist-info/METADATA
bruhapy-2020.12.13.dist-info/WHEEL
bruhapy-2020.12.13.dist-info/top_level.txt
bruhapy-2020.12.13.dist-info/RECORD
