Metadata-Version: 2.1
Name: bruhapy
Version: 2020.12.13
Summary: An API wrapper for https://bruhapi.xyz
Home-page: https://github.com/isigebengu-mikey/bruhapy
Author: mikey
Author-email: mikey@mikeyo.ml
License: UNKNOWN
Platform: UNKNOWN
Classifier: Programming Language :: Python :: 3
Classifier: License :: OSI Approved :: MIT License
Classifier: Operating System :: OS Independent
Requires-Python: >=3.6
